minecraft_bds/__init__.py
minecraft_bds/core.py
minecraft_bds/installer.py
minecraft_bds-1.6.2.dist-info/licenses/LICENSE
minecraft_bds-1.6.2.dist-info/METADATA
minecraft_bds-1.6.2.dist-info/WHEEL
minecraft_bds-1.6.2.dist-info/top_level.txt
minecraft_bds-1.6.2.dist-info/RECORD
