Metadata-Version: 2.4
Name: minecraft-bds
Version: 1.6.2
Summary: Full Python bridge for Minecraft Bedrock Dedicated Server automation
License: MIT
Classifier: Programming Language :: Python :: 3
Classifier: Topic :: Games/Entertainment
Classifier: License :: OSI Approved :: MIT License
Requires-Python: >=3.9
License-File: LICENSE
Dynamic: license-file
